print_easy.py
print_easy-1.8.0.dist-info/DESCRIPTION.rst
print_easy-1.8.0.dist-info/METADATA
print_easy-1.8.0.dist-info/RECORD
print_easy-1.8.0.dist-info/WHEEL
print_easy-1.8.0.dist-info/metadata.json
print_easy-1.8.0.dist-info/top_level.txt
