Metadata-Version: 2.0
Name: print-easy
Version: 1.8.0
Summary: A easy printor, for nested list, stdout or print to file.
Home-page: UNKNOWN
Author: Eric Chen
Author-email: chenyongyuan@sina.com
License: UNKNOWN
Platform: UNKNOWN
